{
  "schema_version": "1.0",
  "capture_metadata": {
    "model_name": "depthwise_separable_conv_optimized",
    "torch_version": "2.11.0+cu128",
    "cuda_version": null,
    "compile_mode": "depthwise_separable_conv_opt",
    "nsys_report_path": "/home/ubuntu/Profiler/examples/depthwise_separable_conv/profiler_output/depthwise_separable_conv_optimized.nsys-rep",
    "ncu_report_path": "/home/ubuntu/Profiler/examples/depthwise_separable_conv/profiler_output/ncu_reps",
    "capture_timestamp_utc": "2026-05-29T02:12:04.444505+00:00",
    "device_name": "NVIDIA RTX PRO 6000 Blackwell Server Edition"
  },
  "operators": [
    {
      "operator_id": "aten::cudnn_convolution, op_id = 6, sizes = [[16, 32, 56, 56], [32, 1, 3, 3], [], [], [], [], [], [], []], input_op_ids = [(0,-1), (0,-1), (0,-1), (0,-1), (0,-1), (0,-1), (0,-1), (0,-1), (0,-1)]_0",
      "operator_name": "aten::cudnn_convolution, op_id = 6, sizes = [[16, 32, 56, 56], [32, 1, 3, 3], [], [], [], [], [], [], []], input_op_ids = [(0,-1), (0,-1), (0,-1), (0,-1), (0,-1), (0,-1), (0,-1), (0,-1), (0,-1)]",
      "call_index": 0,
      "is_fused": true,
      "fused_with": [
        "aten::_convolution, op_id = 5, sizes = [[16, 32, 56, 56], [32, 1, 3, 3], [], [], [], [], [], [], [], [], [], [], []], input_op_ids = [(0,-1), (0,-1), (0,-1), (0,-1), (0,-1), (0,-1), (0,-1), (0,-1), (0,-1), (0,-1), (0,-1), (0,-1), (0,-1)]",
        "aten::convolution, op_id = 4, sizes = [[16, 32, 56, 56], [32, 1, 3, 3], [], [], [], [], [], [], []], input_op_ids = [(0,-1), (0,-1), (0,-1), (0,-1), (0,-1), (0,-1), (0,-1), (0,-1), (0,-1)]"
      ],
      "nvtx_range": {
        "text": "aten::cudnn_convolution, op_id = 6, sizes = [[16, 32, 56, 56], [32, 1, 3, 3], [], [], [], [], [], [], []], input_op_ids = [(0,-1), (0,-1), (0,-1), (0,-1), (0,-1), (0,-1), (0,-1), (0,-1), (0,-1)]",
        "depth": 0,
        "start_ns": 4878989902,
        "end_ns": 4879017293,
        "domain": "default"
      },
      "kernels": [
        {
          "kernel_id": "k_00057",
          "kernel_name": "conv2d_c1_k1_nhwc",
          "demangled_name": null,
          "stream_id": 7,
          "device_id": 0,
          "start_ns": 4879013662,
          "end_ns": 4879019326,
          "duration_ns": 5664,
          "grid_dim": [
            1568,
            1,
            1
          ],
          "block_dim": [
            256,
            1,
            1
          ],
          "metrics": {
            "raw": {
              "dram__bytes_op_read.sum": 6.43,
              "dram__bytes_op_write.sum": 0,
              "dram__throughput.avg.pct_of_peak_sustained_elapsed": 44.18,
              "fbpa__dram_read_bytes.sum": 6.43,
              "fbpa__dram_write_bytes.sum": 0,
              "gpu__dram_throughput.avg.pct_of_peak_sustained_elapsed": 45.88,
              "gpu__time_duration.sum": 9.18,
              "l1tex__t_output_wavefronts_pipe_lsu_mem_local.sum": 0,
              "l1tex__t_sector_hit_rate.pct": 85.96,
              "l1tex__throughput.avg.pct_of_peak_sustained_active": 35.28,
              "launch__registers_per_thread": 40,
              "launch__shared_mem_per_block_dynamic": 0,
              "lts__t_request_hit_rate.pct": 36.85,
              "lts__t_sector_hit_rate.pct": 38.55,
              "sm__cycles_active.sum": 2133508,
              "sm__throughput.avg.pct_of_peak_sustained_elapsed": 23.9,
              "sm__warps_active.avg.pct_of_peak_sustained_active": 78.88,
              "smsp__average_thread_inst_executed_per_inst_executed.ratio": 32,
              "smsp__inst_executed.avg.per_cycle_active": 0.34,
              "smsp__inst_executed.sum": 3013504,
              "smsp__issue_active.avg.pct_of_peak_sustained_active": 34.35,
              "smsp__pipe_tensor_cycles_active.avg.pct_of_peak_sustained_active": 0
            }
          },
          "attribution_method": "nvtx",
          "confidence": "medium",
          "nvtx_range": {
            "text": "aten::cudnn_convolution, op_id = 6, sizes = [[16, 32, 56, 56], [32, 1, 3, 3], [], [], [], [], [], [], []], input_op_ids = [(0,-1), (0,-1), (0,-1), (0,-1), (0,-1), (0,-1), (0,-1), (0,-1), (0,-1)]",
            "depth": 0,
            "start_ns": 4878989902,
            "end_ns": 4879017293,
            "domain": "default"
          }
        }
      ],
      "aggregated": {
        "total_duration_ns": 5664,
        "kernel_count": 1,
        "dominant_kernel_id": "k_00057",
        "total_dram_bytes_read": 6,
        "total_dram_bytes_written": 0,
        "memory_throughput_pct": 45.88,
        "dram_throughput_pct": 44.18,
        "mem_busy_pct": 35.28,
        "l1_hit_rate": 85.96,
        "l2_hit_rate": 36.85,
        "sm_throughput_pct": 23.900000000000002,
        "tensor_core_active_pct": 0.0,
        "achieved_occupancy": 78.88,
        "warp_cycles_per_instruction": null,
        "eligible_cycles_pct": 34.35,
        "total_executed_instructions": 3013504,
        "total_issued_instructions": 0,
        "ipc_active": 0.34,
        "avg_threads_per_warp": 32.0,
        "registers_per_thread": 40.0,
        "local_memory_spills": 0,
        "dynamic_smem_per_block": 0.0
      }
    },
    {
      "operator_id": "aten::mm, op_id = 9, sizes = [[50176, 32], [32, 64], [50176, 64]], input_op_ids = [(0,-1), (0,-1), (0,-1)]_0",
      "operator_name": "aten::mm, op_id = 9, sizes = [[50176, 32], [32, 64], [50176, 64]], input_op_ids = [(0,-1), (0,-1), (0,-1)]",
      "call_index": 0,
      "is_fused": false,
      "fused_with": [],
      "nvtx_range": {
        "text": "aten::mm, op_id = 9, sizes = [[50176, 32], [32, 64], [50176, 64]], input_op_ids = [(0,-1), (0,-1), (0,-1)]",
        "depth": 0,
        "start_ns": 4879102954,
        "end_ns": 4879132125,
        "domain": "default"
      },
      "kernels": [
        {
          "kernel_id": "k_00060",
          "kernel_name": "Kernel2",
          "demangled_name": null,
          "stream_id": 7,
          "device_id": 0,
          "start_ns": 4879131069,
          "end_ns": 4879141661,
          "duration_ns": 10592,
          "grid_dim": [
            784,
            1,
            1
          ],
          "block_dim": [
            128,
            1,
            1
          ],
          "metrics": {
            "raw": {
              "dram__bytes_op_read.sum": 6.45,
              "dram__bytes_op_write.sum": 0,
              "dram__throughput.avg.pct_of_peak_sustained_elapsed": 31.05,
              "fbpa__dram_read_bytes.sum": 6.45,
              "fbpa__dram_write_bytes.sum": 0,
              "gpu__dram_throughput.avg.pct_of_peak_sustained_elapsed": 31.36,
              "gpu__time_duration.sum": 13.06,
              "l1tex__t_output_wavefronts_pipe_lsu_mem_local.sum": 0,
              "l1tex__t_sector_hit_rate.pct": 0,
              "l1tex__throughput.avg.pct_of_peak_sustained_active": 26.56,
              "launch__registers_per_thread": 88,
              "launch__shared_mem_per_block_dynamic": 49.15,
              "lts__t_request_hit_rate.pct": 49.21,
              "lts__t_sector_hit_rate.pct": 34.21,
              "sm__cycles_active.sum": 3188687,
              "sm__throughput.avg.pct_of_peak_sustained_elapsed": 14.23,
              "sm__warps_active.avg.pct_of_peak_sustained_active": 15.42,
              "smsp__average_thread_inst_executed_per_inst_executed.ratio": 32,
              "smsp__inst_executed.avg.per_cycle_active": 0.18,
              "smsp__inst_executed.sum": 2320640,
              "smsp__issue_active.avg.pct_of_peak_sustained_active": 17.81,
              "smsp__pipe_tensor_cycles_active.avg.pct_of_peak_sustained_active": 12.32
            }
          },
          "attribution_method": "nvtx",
          "confidence": "medium",
          "nvtx_range": {
            "text": "aten::mm, op_id = 9, sizes = [[50176, 32], [32, 64], [50176, 64]], input_op_ids = [(0,-1), (0,-1), (0,-1)]",
            "depth": 0,
            "start_ns": 4879102954,
            "end_ns": 4879132125,
            "domain": "default"
          }
        }
      ],
      "aggregated": {
        "total_duration_ns": 10592,
        "kernel_count": 1,
        "dominant_kernel_id": "k_00060",
        "total_dram_bytes_read": 6,
        "total_dram_bytes_written": 0,
        "memory_throughput_pct": 31.36,
        "dram_throughput_pct": 31.050000000000004,
        "mem_busy_pct": 26.559999999999995,
        "l1_hit_rate": 0.0,
        "l2_hit_rate": 49.21,
        "sm_throughput_pct": 14.23,
        "tensor_core_active_pct": 12.32,
        "achieved_occupancy": 15.419999999999998,
        "warp_cycles_per_instruction": null,
        "eligible_cycles_pct": 17.81,
        "total_executed_instructions": 2320640,
        "total_issued_instructions": 0,
        "ipc_active": 0.18,
        "avg_threads_per_warp": 32.0,
        "registers_per_thread": 88.0,
        "local_memory_spills": 0,
        "dynamic_smem_per_block": 49.15
      }
    },
    {
      "operator_id": "aten::cudnn_convolution, op_id = 14, sizes = [[16, 64, 56, 56], [64, 1, 3, 3], [], [], [], [], [], [], []], input_op_ids = [(0,-1), (9,0), (0,-1), (0,-1), (0,-1), (0,-1), (0,-1), (0,-1), (0,-1)]_0",
      "operator_name": "aten::cudnn_convolution, op_id = 14, sizes = [[16, 64, 56, 56], [64, 1, 3, 3], [], [], [], [], [], [], []], input_op_ids = [(0,-1), (9,0), (0,-1), (0,-1), (0,-1), (0,-1), (0,-1), (0,-1), (0,-1)]",
      "call_index": 0,
      "is_fused": true,
      "fused_with": [
        "aten::_convolution, op_id = 13, sizes = [[16, 64, 56, 56], [64, 1, 3, 3], [], [], [], [], [], [], [], [], [], [], []], input_op_ids = [(0,-1), (9,0), (0,-1), (0,-1), (0,-1), (0,-1), (0,-1), (0,-1), (0,-1), (0,-1), (0,-1), (0,-1), (0,-1)]",
        "aten::convolution, op_id = 12, sizes = [[16, 64, 56, 56], [64, 1, 3, 3], [], [], [], [], [], [], []], input_op_ids = [(0,-1), (9,0), (0,-1), (0,-1), (0,-1), (0,-1), (0,-1), (0,-1), (0,-1)]"
      ],
      "nvtx_range": {
        "text": "aten::cudnn_convolution, op_id = 14, sizes = [[16, 64, 56, 56], [64, 1, 3, 3], [], [], [], [], [], [], []], input_op_ids = [(0,-1), (9,0), (0,-1), (0,-1), (0,-1), (0,-1), (0,-1), (0,-1), (0,-1)]",
        "depth": 0,
        "start_ns": 4879230956,
        "end_ns": 4879252676,
        "domain": "default"
      },
      "kernels": [
        {
          "kernel_id": "k_00063",
          "kernel_name": "conv2d_c1_k1_nhwc",
          "demangled_name": null,
          "stream_id": 7,
          "device_id": 0,
          "start_ns": 4879250556,
          "end_ns": 4879259196,
          "duration_ns": 8640,
          "grid_dim": [
            3136,
            1,
            1
          ],
          "block_dim": [
            256,
            1,
            1
          ],
          "metrics": {
            "raw": {
              "dram__bytes_op_read.sum": 12.86,
              "dram__bytes_op_write.sum": 0,
              "dram__throughput.avg.pct_of_peak_sustained_elapsed": 57.38,
              "fbpa__dram_read_bytes.sum": 12.86,
              "fbpa__dram_write_bytes.sum": 0,
              "gpu__dram_throughput.avg.pct_of_peak_sustained_elapsed": 59.93,
              "gpu__time_duration.sum": 14.11,
              "l1tex__t_output_wavefronts_pipe_lsu_mem_local.sum": 0,
              "l1tex__t_sector_hit_rate.pct": 85.07,
              "l1tex__throughput.avg.pct_of_peak_sustained_active": 39.41,
              "launch__registers_per_thread": 40,
              "launch__shared_mem_per_block_dynamic": 0,
              "lts__t_request_hit_rate.pct": 41.04,
              "lts__t_sector_hit_rate.pct": 41.8,
              "sm__cycles_active.sum": 3819724,
              "sm__throughput.avg.pct_of_peak_sustained_elapsed": 31.26,
              "sm__warps_active.avg.pct_of_peak_sustained_active": 80.91,
              "smsp__average_thread_inst_executed_per_inst_executed.ratio": 32,
              "smsp__inst_executed.avg.per_cycle_active": 0.4,
              "smsp__inst_executed.sum": 6027008,
              "smsp__issue_active.avg.pct_of_peak_sustained_active": 40.01,
              "smsp__pipe_tensor_cycles_active.avg.pct_of_peak_sustained_active": 0
            }
          },
          "attribution_method": "nvtx",
          "confidence": "medium",
          "nvtx_range": {
            "text": "aten::cudnn_convolution, op_id = 14, sizes = [[16, 64, 56, 56], [64, 1, 3, 3], [], [], [], [], [], [], []], input_op_ids = [(0,-1), (9,0), (0,-1), (0,-1), (0,-1), (0,-1), (0,-1), (0,-1), (0,-1)]",
            "depth": 0,
            "start_ns": 4879230956,
            "end_ns": 4879252676,
            "domain": "default"
          }
        }
      ],
      "aggregated": {
        "total_duration_ns": 8640,
        "kernel_count": 1,
        "dominant_kernel_id": "k_00063",
        "total_dram_bytes_read": 12,
        "total_dram_bytes_written": 0,
        "memory_throughput_pct": 59.93,
        "dram_throughput_pct": 57.38,
        "mem_busy_pct": 39.41,
        "l1_hit_rate": 85.07,
        "l2_hit_rate": 41.04,
        "sm_throughput_pct": 31.26,
        "tensor_core_active_pct": 0.0,
        "achieved_occupancy": 80.91,
        "warp_cycles_per_instruction": null,
        "eligible_cycles_pct": 40.01,
        "total_executed_instructions": 6027008,
        "total_issued_instructions": 0,
        "ipc_active": 0.4,
        "avg_threads_per_warp": 32.0,
        "registers_per_thread": 40.0,
        "local_memory_spills": 0,
        "dynamic_smem_per_block": 0.0
      }
    },
    {
      "operator_id": "aten::mm, op_id = 17, sizes = [[50176, 64], [64, 128], [50176, 128]], input_op_ids = [(0,-1), (0,-1), (0,-1)]_0",
      "operator_name": "aten::mm, op_id = 17, sizes = [[50176, 64], [64, 128], [50176, 128]], input_op_ids = [(0,-1), (0,-1), (0,-1)]",
      "call_index": 0,
      "is_fused": false,
      "fused_with": [],
      "nvtx_range": {
        "text": "aten::mm, op_id = 17, sizes = [[50176, 64], [64, 128], [50176, 128]], input_op_ids = [(0,-1), (0,-1), (0,-1)]",
        "depth": 0,
        "start_ns": 4879312757,
        "end_ns": 4879328748,
        "domain": "default"
      },
      "kernels": [
        {
          "kernel_id": "k_00066",
          "kernel_name": "Kernel2",
          "demangled_name": null,
          "stream_id": 7,
          "device_id": 0,
          "start_ns": 4879329212,
          "end_ns": 4879348892,
          "duration_ns": 19680,
          "grid_dim": [
            1568,
            1,
            1
          ],
          "block_dim": [
            128,
            1,
            1
          ],
          "metrics": {
            "raw": {
              "dram__bytes_op_read.sum": 12.9,
              "dram__bytes_op_write.sum": 0,
              "dram__throughput.avg.pct_of_peak_sustained_elapsed": 37.1,
              "fbpa__dram_read_bytes.sum": 12.9,
              "fbpa__dram_write_bytes.sum": 0,
              "gpu__dram_throughput.avg.pct_of_peak_sustained_elapsed": 37.87,
              "gpu__time_duration.sum": 21.82,
              "l1tex__t_output_wavefronts_pipe_lsu_mem_local.sum": 0,
              "l1tex__t_sector_hit_rate.pct": 0,
              "l1tex__throughput.avg.pct_of_peak_sustained_active": 34.07,
              "launch__registers_per_thread": 88,
              "launch__shared_mem_per_block_dynamic": 49.15,
              "lts__t_request_hit_rate.pct": 69.59,
              "lts__t_sector_hit_rate.pct": 54.03,
              "sm__cycles_active.sum": 6184644,
              "sm__throughput.avg.pct_of_peak_sustained_elapsed": 22.42,
              "sm__warps_active.avg.pct_of_peak_sustained_active": 15.62,
              "smsp__average_thread_inst_executed_per_inst_executed.ratio": 32,
              "smsp__inst_executed.avg.per_cycle_active": 0.24,
              "smsp__inst_executed.sum": 5908224,
              "smsp__issue_active.avg.pct_of_peak_sustained_active": 23.91,
              "smsp__pipe_tensor_cycles_active.avg.pct_of_peak_sustained_active": 25.99
            }
          },
          "attribution_method": "nvtx",
          "confidence": "medium",
          "nvtx_range": {
            "text": "aten::mm, op_id = 17, sizes = [[50176, 64], [64, 128], [50176, 128]], input_op_ids = [(0,-1), (0,-1), (0,-1)]",
            "depth": 0,
            "start_ns": 4879312757,
            "end_ns": 4879328748,
            "domain": "default"
          }
        }
      ],
      "aggregated": {
        "total_duration_ns": 19680,
        "kernel_count": 1,
        "dominant_kernel_id": "k_00066",
        "total_dram_bytes_read": 12,
        "total_dram_bytes_written": 0,
        "memory_throughput_pct": 37.87,
        "dram_throughput_pct": 37.1,
        "mem_busy_pct": 34.07,
        "l1_hit_rate": 0.0,
        "l2_hit_rate": 69.59,
        "sm_throughput_pct": 22.42,
        "tensor_core_active_pct": 25.99,
        "achieved_occupancy": 15.62,
        "warp_cycles_per_instruction": null,
        "eligible_cycles_pct": 23.91,
        "total_executed_instructions": 5908224,
        "total_issued_instructions": 0,
        "ipc_active": 0.24,
        "avg_threads_per_warp": 32.0,
        "registers_per_thread": 88.0,
        "local_memory_spills": 0,
        "dynamic_smem_per_block": 49.15
      }
    },
    {
      "operator_id": "aten::cudnn_convolution, op_id = 22, sizes = [[16, 128, 56, 56], [128, 1, 3, 3], [], [], [], [], [], [], []], input_op_ids = [(9,0), (17,0), (0,-1), (0,-1), (0,-1), (0,-1), (0,-1), (0,-1), (0,-1)]_0",
      "operator_name": "aten::cudnn_convolution, op_id = 22, sizes = [[16, 128, 56, 56], [128, 1, 3, 3], [], [], [], [], [], [], []], input_op_ids = [(9,0), (17,0), (0,-1), (0,-1), (0,-1), (0,-1), (0,-1), (0,-1), (0,-1)]",
      "call_index": 0,
      "is_fused": true,
      "fused_with": [
        "aten::_convolution, op_id = 21, sizes = [[16, 128, 56, 56], [128, 1, 3, 3], [], [], [], [], [], [], [], [], [], [], []], input_op_ids = [(9,0), (17,0), (0,-1), (0,-1), (0,-1), (0,-1), (0,-1), (0,-1), (0,-1), (0,-1), (0,-1), (0,-1), (0,-1)]",
        "aten::convolution, op_id = 20, sizes = [[16, 128, 56, 56], [128, 1, 3, 3], [], [], [], [], [], [], []], input_op_ids = [(9,0), (17,0), (0,-1), (0,-1), (0,-1), (0,-1), (0,-1), (0,-1), (0,-1)]"
      ],
      "nvtx_range": {
        "text": "aten::cudnn_convolution, op_id = 22, sizes = [[16, 128, 56, 56], [128, 1, 3, 3], [], [], [], [], [], [], []], input_op_ids = [(9,0), (17,0), (0,-1), (0,-1), (0,-1), (0,-1), (0,-1), (0,-1), (0,-1)]",
        "depth": 0,
        "start_ns": 4879393580,
        "end_ns": 4879410429,
        "domain": "default"
      },
      "kernels": [
        {
          "kernel_id": "k_00069",
          "kernel_name": "conv2d_c1_k1_nhwc",
          "demangled_name": null,
          "stream_id": 7,
          "device_id": 0,
          "start_ns": 4879409979,
          "end_ns": 4879426779,
          "duration_ns": 16800,
          "grid_dim": [
            6272,
            1,
            1
          ],
          "block_dim": [
            256,
            1,
            1
          ],
          "metrics": {
            "raw": {
              "dram__bytes_op_read.sum": 25.7,
              "dram__bytes_op_write.sum": 0,
              "dram__throughput.avg.pct_of_peak_sustained_elapsed": 71.16,
              "fbpa__dram_read_bytes.sum": 25.7,
              "fbpa__dram_write_bytes.sum": 0,
              "gpu__dram_throughput.avg.pct_of_peak_sustained_elapsed": 73.44,
              "gpu__time_duration.sum": 22.69,
              "l1tex__t_output_wavefronts_pipe_lsu_mem_local.sum": 0,
              "l1tex__t_sector_hit_rate.pct": 82.91,
              "l1tex__throughput.avg.pct_of_peak_sustained_active": 45.12,
              "launch__registers_per_thread": 40,
              "launch__shared_mem_per_block_dynamic": 0,
              "lts__t_request_hit_rate.pct": 48.65,
              "lts__t_sector_hit_rate.pct": 48.86,
              "sm__cycles_active.sum": 6672714,
              "sm__throughput.avg.pct_of_peak_sustained_elapsed": 39.12,
              "sm__warps_active.avg.pct_of_peak_sustained_active": 86.51,
              "smsp__average_thread_inst_executed_per_inst_executed.ratio": 32,
              "smsp__inst_executed.avg.per_cycle_active": 0.45,
              "smsp__inst_executed.sum": 12054016,
              "smsp__issue_active.avg.pct_of_peak_sustained_active": 44.83,
              "smsp__pipe_tensor_cycles_active.avg.pct_of_peak_sustained_active": 0
            }
          },
          "attribution_method": "nvtx",
          "confidence": "medium",
          "nvtx_range": {
            "text": "aten::cudnn_convolution, op_id = 22, sizes = [[16, 128, 56, 56], [128, 1, 3, 3], [], [], [], [], [], [], []], input_op_ids = [(9,0), (17,0), (0,-1), (0,-1), (0,-1), (0,-1), (0,-1), (0,-1), (0,-1)]",
            "depth": 0,
            "start_ns": 4879393580,
            "end_ns": 4879410429,
            "domain": "default"
          }
        }
      ],
      "aggregated": {
        "total_duration_ns": 16800,
        "kernel_count": 1,
        "dominant_kernel_id": "k_00069",
        "total_dram_bytes_read": 25,
        "total_dram_bytes_written": 0,
        "memory_throughput_pct": 73.44,
        "dram_throughput_pct": 71.16,
        "mem_busy_pct": 45.12,
        "l1_hit_rate": 82.91,
        "l2_hit_rate": 48.65,
        "sm_throughput_pct": 39.12,
        "tensor_core_active_pct": 0.0,
        "achieved_occupancy": 86.51,
        "warp_cycles_per_instruction": null,
        "eligible_cycles_pct": 44.83,
        "total_executed_instructions": 12054016,
        "total_issued_instructions": 0,
        "ipc_active": 0.45,
        "avg_threads_per_warp": 32.0,
        "registers_per_thread": 40.0,
        "local_memory_spills": 0,
        "dynamic_smem_per_block": 0.0
      }
    },
    {
      "operator_id": "aten::mm, op_id = 25, sizes = [[50176, 128], [128, 256], [50176, 256]], input_op_ids = [(0,-1), (0,-1), (9,0)]_0",
      "operator_name": "aten::mm, op_id = 25, sizes = [[50176, 128], [128, 256], [50176, 256]], input_op_ids = [(0,-1), (0,-1), (9,0)]",
      "call_index": 0,
      "is_fused": false,
      "fused_with": [],
      "nvtx_range": {
        "text": "aten::mm, op_id = 25, sizes = [[50176, 128], [128, 256], [50176, 256]], input_op_ids = [(0,-1), (0,-1), (9,0)]",
        "depth": 0,
        "start_ns": 4879462290,
        "end_ns": 4879476530,
        "domain": "default"
      },
      "kernels": [
        {
          "kernel_id": "k_00072",
          "kernel_name": "Kernel2",
          "demangled_name": null,
          "stream_id": 7,
          "device_id": 0,
          "start_ns": 4879476955,
          "end_ns": 4879527355,
          "duration_ns": 50400,
          "grid_dim": [
            784,
            1,
            1
          ],
          "block_dim": [
            128,
            1,
            1
          ],
          "metrics": {
            "raw": {
              "dram__bytes_op_read.sum": 25.86,
              "dram__bytes_op_write.sum": 352,
              "dram__throughput.avg.pct_of_peak_sustained_elapsed": 31.11,
              "fbpa__dram_read_bytes.sum": 25.86,
              "fbpa__dram_write_bytes.sum": 352,
              "gpu__dram_throughput.avg.pct_of_peak_sustained_elapsed": 31.11,
              "gpu__time_duration.sum": 52.83,
              "l1tex__t_output_wavefronts_pipe_lsu_mem_local.sum": 0,
              "l1tex__t_sector_hit_rate.pct": 0,
              "l1tex__throughput.avg.pct_of_peak_sustained_active": 30.01,
              "launch__registers_per_thread": 228,
              "launch__shared_mem_per_block_dynamic": 81.92,
              "lts__t_request_hit_rate.pct": 74.79,
              "lts__t_sector_hit_rate.pct": 60.07,
              "sm__cycles_active.sum": 14588900,
              "sm__throughput.avg.pct_of_peak_sustained_elapsed": 36.2,
              "sm__warps_active.avg.pct_of_peak_sustained_active": 8.34,
              "smsp__average_thread_inst_executed_per_inst_executed.ratio": 32,
              "smsp__inst_executed.avg.per_cycle_active": 0.17,
              "smsp__inst_executed.sum": 9536576,
              "smsp__issue_active.avg.pct_of_peak_sustained_active": 16.58,
              "smsp__pipe_tensor_cycles_active.avg.pct_of_peak_sustained_active": 44.66
            }
          },
          "attribution_method": "nvtx",
          "confidence": "medium",
          "nvtx_range": {
            "text": "aten::mm, op_id = 25, sizes = [[50176, 128], [128, 256], [50176, 256]], input_op_ids = [(0,-1), (0,-1), (9,0)]",
            "depth": 0,
            "start_ns": 4879462290,
            "end_ns": 4879476530,
            "domain": "default"
          }
        }
      ],
      "aggregated": {
        "total_duration_ns": 50400,
        "kernel_count": 1,
        "dominant_kernel_id": "k_00072",
        "total_dram_bytes_read": 25,
        "total_dram_bytes_written": 352,
        "memory_throughput_pct": 31.11,
        "dram_throughput_pct": 31.11,
        "mem_busy_pct": 30.01,
        "l1_hit_rate": 0.0,
        "l2_hit_rate": 74.79,
        "sm_throughput_pct": 36.2,
        "tensor_core_active_pct": 44.66,
        "achieved_occupancy": 8.34,
        "warp_cycles_per_instruction": null,
        "eligible_cycles_pct": 16.58,
        "total_executed_instructions": 9536576,
        "total_issued_instructions": 0,
        "ipc_active": 0.17,
        "avg_threads_per_warp": 32.0,
        "registers_per_thread": 228.0,
        "local_memory_spills": 0,
        "dynamic_smem_per_block": 81.92
      }
    },
    {
      "operator_id": "aten::cudnn_convolution, op_id = 32, sizes = [[16, 32, 56, 56], [32, 1, 3, 3], [], [], [], [], [], [], []], input_op_ids = [(0,-1), (17,0), (0,-1), (0,-1), (0,-1), (0,-1), (0,-1), (0,-1), (0,-1)]_0",
      "operator_name": "aten::cudnn_convolution, op_id = 32, sizes = [[16, 32, 56, 56], [32, 1, 3, 3], [], [], [], [], [], [], []], input_op_ids = [(0,-1), (17,0), (0,-1), (0,-1), (0,-1), (0,-1), (0,-1), (0,-1), (0,-1)]",
      "call_index": 0,
      "is_fused": true,
      "fused_with": [
        "aten::_convolution, op_id = 31, sizes = [[16, 32, 56, 56], [32, 1, 3, 3], [], [], [], [], [], [], [], [], [], [], []], input_op_ids = [(0,-1), (17,0), (0,-1), (0,-1), (0,-1), (0,-1), (0,-1), (0,-1), (0,-1), (0,-1), (0,-1), (0,-1), (0,-1)]",
        "aten::convolution, op_id = 30, sizes = [[16, 32, 56, 56], [32, 1, 3, 3], [], [], [], [], [], [], []], input_op_ids = [(0,-1), (17,0), (0,-1), (0,-1), (0,-1), (0,-1), (0,-1), (0,-1), (0,-1)]"
      ],
      "nvtx_range": {
        "text": "aten::cudnn_convolution, op_id = 32, sizes = [[16, 32, 56, 56], [32, 1, 3, 3], [], [], [], [], [], [], []], input_op_ids = [(0,-1), (17,0), (0,-1), (0,-1), (0,-1), (0,-1), (0,-1), (0,-1), (0,-1)]",
        "depth": 0,
        "start_ns": 4879592583,
        "end_ns": 4879609263,
        "domain": "default"
      },
      "kernels": [
        {
          "kernel_id": "k_00075",
          "kernel_name": "conv2d_c1_k1_nhwc",
          "demangled_name": null,
          "stream_id": 7,
          "device_id": 0,
          "start_ns": 4879608346,
          "end_ns": 4879614042,
          "duration_ns": 5696,
          "grid_dim": [
            1568,
            1,
            1
          ],
          "block_dim": [
            256,
            1,
            1
          ],
          "metrics": {
            "raw": {
              "dram__bytes_op_read.sum": 6.43,
              "dram__bytes_op_write.sum": 0,
              "dram__throughput.avg.pct_of_peak_sustained_elapsed": 45.36,
              "fbpa__dram_read_bytes.sum": 6.43,
              "fbpa__dram_write_bytes.sum": 0,
              "gpu__dram_throughput.avg.pct_of_peak_sustained_elapsed": 47.21,
              "gpu__time_duration.sum": 8.93,
              "l1tex__t_output_wavefronts_pipe_lsu_mem_local.sum": 0,
              "l1tex__t_sector_hit_rate.pct": 85.96,
              "l1tex__throughput.avg.pct_of_peak_sustained_active": 35.06,
              "launch__registers_per_thread": 40,
              "launch__shared_mem_per_block_dynamic": 0,
              "lts__t_request_hit_rate.pct": 36.84,
              "lts__t_sector_hit_rate.pct": 38.54,
              "sm__cycles_active.sum": 2146425,
              "sm__throughput.avg.pct_of_peak_sustained_elapsed": 24.57,
              "sm__warps_active.avg.pct_of_peak_sustained_active": 74.2,
              "smsp__average_thread_inst_executed_per_inst_executed.ratio": 32,
              "smsp__inst_executed.avg.per_cycle_active": 0.35,
              "smsp__inst_executed.sum": 3013504,
              "smsp__issue_active.avg.pct_of_peak_sustained_active": 34.92,
              "smsp__pipe_tensor_cycles_active.avg.pct_of_peak_sustained_active": 0
            }
          },
          "attribution_method": "nvtx",
          "confidence": "medium",
          "nvtx_range": {
            "text": "aten::cudnn_convolution, op_id = 32, sizes = [[16, 32, 56, 56], [32, 1, 3, 3], [], [], [], [], [], [], []], input_op_ids = [(0,-1), (17,0), (0,-1), (0,-1), (0,-1), (0,-1), (0,-1), (0,-1), (0,-1)]",
            "depth": 0,
            "start_ns": 4879592583,
            "end_ns": 4879609263,
            "domain": "default"
          }
        }
      ],
      "aggregated": {
        "total_duration_ns": 5696,
        "kernel_count": 1,
        "dominant_kernel_id": "k_00075",
        "total_dram_bytes_read": 6,
        "total_dram_bytes_written": 0,
        "memory_throughput_pct": 47.21000000000001,
        "dram_throughput_pct": 45.36,
        "mem_busy_pct": 35.06,
        "l1_hit_rate": 85.96,
        "l2_hit_rate": 36.84,
        "sm_throughput_pct": 24.57,
        "tensor_core_active_pct": 0.0,
        "achieved_occupancy": 74.2,
        "warp_cycles_per_instruction": null,
        "eligible_cycles_pct": 34.92,
        "total_executed_instructions": 3013504,
        "total_issued_instructions": 0,
        "ipc_active": 0.35,
        "avg_threads_per_warp": 32.0,
        "registers_per_thread": 40.0,
        "local_memory_spills": 0,
        "dynamic_smem_per_block": 0.0
      }
    },
    {
      "operator_id": "aten::mm, op_id = 35, sizes = [[50176, 32], [32, 64], [50176, 64]], input_op_ids = [(0,-1), (0,-1), (20,0)]_0",
      "operator_name": "aten::mm, op_id = 35, sizes = [[50176, 32], [32, 64], [50176, 64]], input_op_ids = [(0,-1), (0,-1), (20,0)]",
      "call_index": 0,
      "is_fused": false,
      "fused_with": [],
      "nvtx_range": {
        "text": "aten::mm, op_id = 35, sizes = [[50176, 32], [32, 64], [50176, 64]], input_op_ids = [(0,-1), (0,-1), (20,0)]",
        "depth": 0,
        "start_ns": 4879658993,
        "end_ns": 4879673653,
        "domain": "default"
      },
      "kernels": [
        {
          "kernel_id": "k_00078",
          "kernel_name": "Kernel2",
          "demangled_name": null,
          "stream_id": 7,
          "device_id": 0,
          "start_ns": 4879674074,
          "end_ns": 4879684345,
          "duration_ns": 10271,
          "grid_dim": [
            784,
            1,
            1
          ],
          "block_dim": [
            128,
            1,
            1
          ],
          "metrics": {
            "raw": {
              "dram__bytes_op_read.sum": 6.45,
              "dram__bytes_op_write.sum": 0,
              "dram__throughput.avg.pct_of_peak_sustained_elapsed": 31.49,
              "fbpa__dram_read_bytes.sum": 6.45,
              "fbpa__dram_write_bytes.sum": 0,
              "gpu__dram_throughput.avg.pct_of_peak_sustained_elapsed": 31.88,
              "gpu__time_duration.sum": 12.9,
              "l1tex__t_output_wavefronts_pipe_lsu_mem_local.sum": 0,
              "l1tex__t_sector_hit_rate.pct": 0,
              "l1tex__throughput.avg.pct_of_peak_sustained_active": 25.35,
              "launch__registers_per_thread": 88,
              "launch__shared_mem_per_block_dynamic": 49.15,
              "lts__t_request_hit_rate.pct": 49.21,
              "lts__t_sector_hit_rate.pct": 34.2,
              "sm__cycles_active.sum": 3341075,
              "sm__throughput.avg.pct_of_peak_sustained_elapsed": 14.41,
              "sm__warps_active.avg.pct_of_peak_sustained_active": 14.34,
              "smsp__average_thread_inst_executed_per_inst_executed.ratio": 32,
              "smsp__inst_executed.avg.per_cycle_active": 0.18,
              "smsp__inst_executed.sum": 2320640,
              "smsp__issue_active.avg.pct_of_peak_sustained_active": 17.83,
              "smsp__pipe_tensor_cycles_active.avg.pct_of_peak_sustained_active": 12.33
            }
          },
          "attribution_method": "nvtx",
          "confidence": "medium",
          "nvtx_range": {
            "text": "aten::mm, op_id = 35, sizes = [[50176, 32], [32, 64], [50176, 64]], input_op_ids = [(0,-1), (0,-1), (20,0)]",
            "depth": 0,
            "start_ns": 4879658993,
            "end_ns": 4879673653,
            "domain": "default"
          }
        }
      ],
      "aggregated": {
        "total_duration_ns": 10271,
        "kernel_count": 1,
        "dominant_kernel_id": "k_00078",
        "total_dram_bytes_read": 6,
        "total_dram_bytes_written": 0,
        "memory_throughput_pct": 31.88,
        "dram_throughput_pct": 31.49,
        "mem_busy_pct": 25.35,
        "l1_hit_rate": 0.0,
        "l2_hit_rate": 49.21,
        "sm_throughput_pct": 14.410000000000002,
        "tensor_core_active_pct": 12.33,
        "achieved_occupancy": 14.339999999999998,
        "warp_cycles_per_instruction": null,
        "eligible_cycles_pct": 17.83,
        "total_executed_instructions": 2320640,
        "total_issued_instructions": 0,
        "ipc_active": 0.18,
        "avg_threads_per_warp": 32.0,
        "registers_per_thread": 88.0,
        "local_memory_spills": 0,
        "dynamic_smem_per_block": 49.15
      }
    },
    {
      "operator_id": "aten::cudnn_convolution, op_id = 40, sizes = [[16, 64, 56, 56], [64, 1, 3, 3], [], [], [], [], [], [], []], input_op_ids = [(17,0), (35,0), (0,-1), (0,-1), (0,-1), (0,-1), (0,-1), (0,-1), (0,-1)]_0",
      "operator_name": "aten::cudnn_convolution, op_id = 40, sizes = [[16, 64, 56, 56], [64, 1, 3, 3], [], [], [], [], [], [], []], input_op_ids = [(17,0), (35,0), (0,-1), (0,-1), (0,-1), (0,-1), (0,-1), (0,-1), (0,-1)]",
      "call_index": 0,
      "is_fused": true,
      "fused_with": [
        "aten::_convolution, op_id = 39, sizes = [[16, 64, 56, 56], [64, 1, 3, 3], [], [], [], [], [], [], [], [], [], [], []], input_op_ids = [(17,0), (35,0), (0,-1), (0,-1), (0,-1), (0,-1), (0,-1), (0,-1), (0,-1), (0,-1), (0,-1), (0,-1), (0,-1)]",
        "aten::convolution, op_id = 38, sizes = [[16, 64, 56, 56], [64, 1, 3, 3], [], [], [], [], [], [], []], input_op_ids = [(17,0), (35,0), (0,-1), (0,-1), (0,-1), (0,-1), (0,-1), (0,-1), (0,-1)]"
      ],
      "nvtx_range": {
        "text": "aten::cudnn_convolution, op_id = 40, sizes = [[16, 64, 56, 56], [64, 1, 3, 3], [], [], [], [], [], [], []], input_op_ids = [(17,0), (35,0), (0,-1), (0,-1), (0,-1), (0,-1), (0,-1), (0,-1), (0,-1)]",
        "depth": 0,
        "start_ns": 4879729704,
        "end_ns": 4879744505,
        "domain": "default"
      },
      "kernels": [
        {
          "kernel_id": "k_00081",
          "kernel_name": "conv2d_c1_k1_nhwc",
          "demangled_name": null,
          "stream_id": 7,
          "device_id": 0,
          "start_ns": 4879744185,
          "end_ns": 4879752921,
          "duration_ns": 8736,
          "grid_dim": [
            3136,
            1,
            1
          ],
          "block_dim": [
            256,
            1,
            1
          ],
          "metrics": {
            "raw": {
              "dram__bytes_op_read.sum": 12.86,
              "dram__bytes_op_write.sum": 0,
              "dram__throughput.avg.pct_of_peak_sustained_elapsed": 56.9,
              "fbpa__dram_read_bytes.sum": 12.86,
              "fbpa__dram_write_bytes.sum": 0,
              "gpu__dram_throughput.avg.pct_of_peak_sustained_elapsed": 59.35,
              "gpu__time_duration.sum": 14.24,
              "l1tex__t_output_wavefronts_pipe_lsu_mem_local.sum": 0,
              "l1tex__t_sector_hit_rate.pct": 85.06,
              "l1tex__throughput.avg.pct_of_peak_sustained_active": 40.07,
              "launch__registers_per_thread": 40,
              "launch__shared_mem_per_block_dynamic": 0,
              "lts__t_request_hit_rate.pct": 41.07,
              "lts__t_sector_hit_rate.pct": 41.85,
              "sm__cycles_active.sum": 3756634,
              "sm__throughput.avg.pct_of_peak_sustained_elapsed": 30.9,
              "sm__warps_active.avg.pct_of_peak_sustained_active": 83.93,
              "smsp__average_thread_inst_executed_per_inst_executed.ratio": 32,
              "smsp__inst_executed.avg.per_cycle_active": 0.4,
              "smsp__inst_executed.sum": 6027008,
              "smsp__issue_active.avg.pct_of_peak_sustained_active": 40.28,
              "smsp__pipe_tensor_cycles_active.avg.pct_of_peak_sustained_active": 0
            }
          },
          "attribution_method": "nvtx",
          "confidence": "medium",
          "nvtx_range": {
            "text": "aten::cudnn_convolution, op_id = 40, sizes = [[16, 64, 56, 56], [64, 1, 3, 3], [], [], [], [], [], [], []], input_op_ids = [(17,0), (35,0), (0,-1), (0,-1), (0,-1), (0,-1), (0,-1), (0,-1), (0,-1)]",
            "depth": 0,
            "start_ns": 4879729704,
            "end_ns": 4879744505,
            "domain": "default"
          }
        }
      ],
      "aggregated": {
        "total_duration_ns": 8736,
        "kernel_count": 1,
        "dominant_kernel_id": "k_00081",
        "total_dram_bytes_read": 12,
        "total_dram_bytes_written": 0,
        "memory_throughput_pct": 59.35,
        "dram_throughput_pct": 56.9,
        "mem_busy_pct": 40.07,
        "l1_hit_rate": 85.06,
        "l2_hit_rate": 41.07,
        "sm_throughput_pct": 30.899999999999995,
        "tensor_core_active_pct": 0.0,
        "achieved_occupancy": 83.93,
        "warp_cycles_per_instruction": null,
        "eligible_cycles_pct": 40.28,
        "total_executed_instructions": 6027008,
        "total_issued_instructions": 0,
        "ipc_active": 0.4,
        "avg_threads_per_warp": 32.0,
        "registers_per_thread": 40.0,
        "local_memory_spills": 0,
        "dynamic_smem_per_block": 0.0
      }
    },
    {
      "operator_id": "aten::mm, op_id = 43, sizes = [[50176, 64], [64, 128], [50176, 128]], input_op_ids = [(0,-1), (0,-1), (17,0)]_0",
      "operator_name": "aten::mm, op_id = 43, sizes = [[50176, 64], [64, 128], [50176, 128]], input_op_ids = [(0,-1), (0,-1), (17,0)]",
      "call_index": 0,
      "is_fused": false,
      "fused_with": [],
      "nvtx_range": {
        "text": "aten::mm, op_id = 43, sizes = [[50176, 64], [64, 128], [50176, 128]], input_op_ids = [(0,-1), (0,-1), (17,0)]",
        "depth": 0,
        "start_ns": 4879792415,
        "end_ns": 4879805116,
        "domain": "default"
      },
      "kernels": [
        {
          "kernel_id": "k_00084",
          "kernel_name": "Kernel2",
          "demangled_name": null,
          "stream_id": 7,
          "device_id": 0,
          "start_ns": 4879805913,
          "end_ns": 4879825624,
          "duration_ns": 19711,
          "grid_dim": [
            1568,
            1,
            1
          ],
          "block_dim": [
            128,
            1,
            1
          ],
          "metrics": {
            "raw": {
              "dram__bytes_op_read.sum": 12.9,
              "dram__bytes_op_write.sum": 0,
              "dram__throughput.avg.pct_of_peak_sustained_elapsed": 37.37,
              "fbpa__dram_read_bytes.sum": 12.9,
              "fbpa__dram_write_bytes.sum": 0,
              "gpu__dram_throughput.avg.pct_of_peak_sustained_elapsed": 38.18,
              "gpu__time_duration.sum": 21.66,
              "l1tex__t_output_wavefronts_pipe_lsu_mem_local.sum": 0,
              "l1tex__t_sector_hit_rate.pct": 0,
              "l1tex__throughput.avg.pct_of_peak_sustained_active": 34.01,
              "launch__registers_per_thread": 88,
              "launch__shared_mem_per_block_dynamic": 49.15,
              "lts__t_request_hit_rate.pct": 69.59,
              "lts__t_sector_hit_rate.pct": 54.01,
              "sm__cycles_active.sum": 6179848,
              "sm__throughput.avg.pct_of_peak_sustained_elapsed": 22.47,
              "sm__warps_active.avg.pct_of_peak_sustained_active": 15.73,
              "smsp__average_thread_inst_executed_per_inst_executed.ratio": 32,
              "smsp__inst_executed.avg.per_cycle_active": 0.24,
              "smsp__inst_executed.sum": 5908224,
              "smsp__issue_active.avg.pct_of_peak_sustained_active": 24.16,
              "smsp__pipe_tensor_cycles_active.avg.pct_of_peak_sustained_active": 26.27
            }
          },
          "attribution_method": "nvtx",
          "confidence": "medium",
          "nvtx_range": {
            "text": "aten::mm, op_id = 43, sizes = [[50176, 64], [64, 128], [50176, 128]], input_op_ids = [(0,-1), (0,-1), (17,0)]",
            "depth": 0,
            "start_ns": 4879792415,
            "end_ns": 4879805116,
            "domain": "default"
          }
        }
      ],
      "aggregated": {
        "total_duration_ns": 19711,
        "kernel_count": 1,
        "dominant_kernel_id": "k_00084",
        "total_dram_bytes_read": 12,
        "total_dram_bytes_written": 0,
        "memory_throughput_pct": 38.18,
        "dram_throughput_pct": 37.37,
        "mem_busy_pct": 34.01,
        "l1_hit_rate": 0.0,
        "l2_hit_rate": 69.59,
        "sm_throughput_pct": 22.47,
        "tensor_core_active_pct": 26.27,
        "achieved_occupancy": 15.730000000000002,
        "warp_cycles_per_instruction": null,
        "eligible_cycles_pct": 24.16,
        "total_executed_instructions": 5908224,
        "total_issued_instructions": 0,
        "ipc_active": 0.23999999999999996,
        "avg_threads_per_warp": 32.0,
        "registers_per_thread": 88.0,
        "local_memory_spills": 0,
        "dynamic_smem_per_block": 49.15
      }
    },
    {
      "operator_id": "aten::cudnn_convolution, op_id = 48, sizes = [[16, 128, 56, 56], [128, 1, 3, 3], [], [], [], [], [], [], []], input_op_ids = [(35,0), (43,0), (0,-1), (0,-1), (0,-1), (0,-1), (0,-1), (0,-1), (0,-1)]_0",
      "operator_name": "aten::cudnn_convolution, op_id = 48, sizes = [[16, 128, 56, 56], [128, 1, 3, 3], [], [], [], [], [], [], []], input_op_ids = [(35,0), (43,0), (0,-1), (0,-1), (0,-1), (0,-1), (0,-1), (0,-1), (0,-1)]",
      "call_index": 0,
      "is_fused": true,
      "fused_with": [
        "aten::_convolution, op_id = 47, sizes = [[16, 128, 56, 56], [128, 1, 3, 3], [], [], [], [], [], [], [], [], [], [], []], input_op_ids = [(35,0), (43,0), (0,-1), (0,-1), (0,-1), (0,-1), (0,-1), (0,-1), (0,-1), (0,-1), (0,-1), (0,-1), (0,-1)]",
        "aten::convolution, op_id = 46, sizes = [[16, 128, 56, 56], [128, 1, 3, 3], [], [], [], [], [], [], []], input_op_ids = [(35,0), (43,0), (0,-1), (0,-1), (0,-1), (0,-1), (0,-1), (0,-1), (0,-1)]"
      ],
      "nvtx_range": {
        "text": "aten::cudnn_convolution, op_id = 48, sizes = [[16, 128, 56, 56], [128, 1, 3, 3], [], [], [], [], [], [], []], input_op_ids = [(35,0), (43,0), (0,-1), (0,-1), (0,-1), (0,-1), (0,-1), (0,-1), (0,-1)]",
        "depth": 0,
        "start_ns": 4879857847,
        "end_ns": 4879869887,
        "domain": "default"
      },
      "kernels": [
        {
          "kernel_id": "k_00087",
          "kernel_name": "conv2d_c1_k1_nhwc",
          "demangled_name": null,
          "stream_id": 7,
          "device_id": 0,
          "start_ns": 4879870040,
          "end_ns": 4879887000,
          "duration_ns": 16960,
          "grid_dim": [
            6272,
            1,
            1
          ],
          "block_dim": [
            256,
            1,
            1
          ],
          "metrics": {
            "raw": {
              "dram__bytes_op_read.sum": 25.7,
              "dram__bytes_op_write.sum": 0,
              "dram__throughput.avg.pct_of_peak_sustained_elapsed": 71.21,
              "fbpa__dram_read_bytes.sum": 25.7,
              "fbpa__dram_write_bytes.sum": 0,
              "gpu__dram_throughput.avg.pct_of_peak_sustained_elapsed": 73.66,
              "gpu__time_duration.sum": 22.66,
              "l1tex__t_output_wavefronts_pipe_lsu_mem_local.sum": 0,
              "l1tex__t_sector_hit_rate.pct": 82.91,
              "l1tex__throughput.avg.pct_of_peak_sustained_active": 44.62,
              "launch__registers_per_thread": 40,
              "launch__shared_mem_per_block_dynamic": 0,
              "lts__t_request_hit_rate.pct": 48.67,
              "lts__t_sector_hit_rate.pct": 48.89,
              "sm__cycles_active.sum": 6746703,
              "sm__throughput.avg.pct_of_peak_sustained_elapsed": 38.88,
              "sm__warps_active.avg.pct_of_peak_sustained_active": 86.33,
              "smsp__average_thread_inst_executed_per_inst_executed.ratio": 32,
              "smsp__inst_executed.avg.per_cycle_active": 0.45,
              "smsp__inst_executed.sum": 12054016,
              "smsp__issue_active.avg.pct_of_peak_sustained_active": 44.95,
              "smsp__pipe_tensor_cycles_active.avg.pct_of_peak_sustained_active": 0
            }
          },
          "attribution_method": "nvtx",
          "confidence": "medium",
          "nvtx_range": {
            "text": "aten::cudnn_convolution, op_id = 48, sizes = [[16, 128, 56, 56], [128, 1, 3, 3], [], [], [], [], [], [], []], input_op_ids = [(35,0), (43,0), (0,-1), (0,-1), (0,-1), (0,-1), (0,-1), (0,-1), (0,-1)]",
            "depth": 0,
            "start_ns": 4879857847,
            "end_ns": 4879869887,
            "domain": "default"
          }
        }
      ],
      "aggregated": {
        "total_duration_ns": 16960,
        "kernel_count": 1,
        "dominant_kernel_id": "k_00087",
        "total_dram_bytes_read": 25,
        "total_dram_bytes_written": 0,
        "memory_throughput_pct": 73.66,
        "dram_throughput_pct": 71.21,
        "mem_busy_pct": 44.62,
        "l1_hit_rate": 82.91,
        "l2_hit_rate": 48.67,
        "sm_throughput_pct": 38.88,
        "tensor_core_active_pct": 0.0,
        "achieved_occupancy": 86.33,
        "warp_cycles_per_instruction": null,
        "eligible_cycles_pct": 44.95,
        "total_executed_instructions": 12054016,
        "total_issued_instructions": 0,
        "ipc_active": 0.45,
        "avg_threads_per_warp": 32.0,
        "registers_per_thread": 40.0,
        "local_memory_spills": 0,
        "dynamic_smem_per_block": 0.0
      }
    },
    {
      "operator_id": "aten::mm, op_id = 51, sizes = [[50176, 128], [128, 256], [50176, 256]], input_op_ids = [(0,-1), (0,-1), (35,0)]_0",
      "operator_name": "aten::mm, op_id = 51, sizes = [[50176, 128], [128, 256], [50176, 256]], input_op_ids = [(0,-1), (0,-1), (35,0)]",
      "call_index": 0,
      "is_fused": false,
      "fused_with": [],
      "nvtx_range": {
        "text": "aten::mm, op_id = 51, sizes = [[50176, 128], [128, 256], [50176, 256]], input_op_ids = [(0,-1), (0,-1), (35,0)]",
        "depth": 0,
        "start_ns": 4879905867,
        "end_ns": 4879915788,
        "domain": "default"
      },
      "kernels": [
        {
          "kernel_id": "k_00090",
          "kernel_name": "Kernel2",
          "demangled_name": null,
          "stream_id": 7,
          "device_id": 0,
          "start_ns": 4879916888,
          "end_ns": 4879967223,
          "duration_ns": 50335,
          "grid_dim": [
            784,
            1,
            1
          ],
          "block_dim": [
            128,
            1,
            1
          ],
          "metrics": {
            "raw": {
              "dram__bytes_op_read.sum": 25.86,
              "dram__bytes_op_write.sum": 239.62,
              "dram__throughput.avg.pct_of_peak_sustained_elapsed": 31.26,
              "fbpa__dram_read_bytes.sum": 25.86,
              "fbpa__dram_write_bytes.sum": 239.62,
              "gpu__dram_throughput.avg.pct_of_peak_sustained_elapsed": 31.26,
              "gpu__time_duration.sum": 52.35,
              "l1tex__t_output_wavefronts_pipe_lsu_mem_local.sum": 0,
              "l1tex__t_sector_hit_rate.pct": 0,
              "l1tex__throughput.avg.pct_of_peak_sustained_active": 30.4,
              "launch__registers_per_thread": 228,
              "launch__shared_mem_per_block_dynamic": 81.92,
              "lts__t_request_hit_rate.pct": 74.79,
              "lts__t_sector_hit_rate.pct": 60.07,
              "sm__cycles_active.sum": 14496843,
              "sm__throughput.avg.pct_of_peak_sustained_elapsed": 36.67,
              "sm__warps_active.avg.pct_of_peak_sustained_active": 8.25,
              "smsp__average_thread_inst_executed_per_inst_executed.ratio": 32,
              "smsp__inst_executed.avg.per_cycle_active": 0.17,
              "smsp__inst_executed.sum": 9536576,
              "smsp__issue_active.avg.pct_of_peak_sustained_active": 16.7,
              "smsp__pipe_tensor_cycles_active.avg.pct_of_peak_sustained_active": 44.99
            }
          },
          "attribution_method": "nvtx",
          "confidence": "medium",
          "nvtx_range": {
            "text": "aten::mm, op_id = 51, sizes = [[50176, 128], [128, 256], [50176, 256]], input_op_ids = [(0,-1), (0,-1), (35,0)]",
            "depth": 0,
            "start_ns": 4879905867,
            "end_ns": 4879915788,
            "domain": "default"
          }
        }
      ],
      "aggregated": {
        "total_duration_ns": 50335,
        "kernel_count": 1,
        "dominant_kernel_id": "k_00090",
        "total_dram_bytes_read": 25,
        "total_dram_bytes_written": 239,
        "memory_throughput_pct": 31.26,
        "dram_throughput_pct": 31.26,
        "mem_busy_pct": 30.4,
        "l1_hit_rate": 0.0,
        "l2_hit_rate": 74.79,
        "sm_throughput_pct": 36.67,
        "tensor_core_active_pct": 44.989999999999995,
        "achieved_occupancy": 8.25,
        "warp_cycles_per_instruction": null,
        "eligible_cycles_pct": 16.7,
        "total_executed_instructions": 9536576,
        "total_issued_instructions": 0,
        "ipc_active": 0.17,
        "avg_threads_per_warp": 32.0,
        "registers_per_thread": 228.0,
        "local_memory_spills": 0,
        "dynamic_smem_per_block": 81.92
      }
    }
  ],
  "unattributed_kernels": [
    {
      "kernel_id": "k_00056",
      "kernel_name": "triton_poi_fused__native_batch_1...",
      "demangled_name": null,
      "stream_id": 7,
      "device_id": 0,
      "start_ns": 4878941695,
      "end_ns": 4878942655,
      "duration_ns": 960,
      "grid_dim": [
        2,
        1,
        1
      ],
      "block_dim": [
        128,
        1,
        1
      ],
      "metrics": {
        "raw": {}
      },
      "attribution_method": "unattributed",
      "confidence": "unattributed",
      "nvtx_range": null
    },
    {
      "kernel_id": "k_00058",
      "kernel_name": "triton_poi_fused__native_batch_2...",
      "demangled_name": null,
      "stream_id": 7,
      "device_id": 0,
      "start_ns": 4879062270,
      "end_ns": 4879066590,
      "duration_ns": 4320,
      "grid_dim": [
        1568,
        1,
        1
      ],
      "block_dim": [
        128,
        1,
        1
      ],
      "metrics": {
        "raw": {}
      },
      "attribution_method": "unattributed",
      "confidence": "unattributed",
      "nvtx_range": null
    },
    {
      "kernel_id": "k_00059",
      "kernel_name": "triton_poi_fused__native_batch_3...",
      "demangled_name": null,
      "stream_id": 7,
      "device_id": 0,
      "start_ns": 4879092318,
      "end_ns": 4879093278,
      "duration_ns": 960,
      "grid_dim": [
        1,
        4,
        1
      ],
      "block_dim": [
        128,
        1,
        1
      ],
      "metrics": {
        "raw": {}
      },
      "attribution_method": "unattributed",
      "confidence": "unattributed",
      "nvtx_range": null
    },
    {
      "kernel_id": "k_00061",
      "kernel_name": "triton_poi_fused__native_batch_4...",
      "demangled_name": null,
      "stream_id": 7,
      "device_id": 0,
      "start_ns": 4879172349,
      "end_ns": 4879179517,
      "duration_ns": 7168,
      "grid_dim": [
        3136,
        1,
        1
      ],
      "block_dim": [
        128,
        1,
        1
      ],
      "metrics": {
        "raw": {}
      },
      "attribution_method": "unattributed",
      "confidence": "unattributed",
      "nvtx_range": null
    },
    {
      "kernel_id": "k_00062",
      "kernel_name": "triton_poi_fused__native_batch_5...",
      "demangled_name": null,
      "stream_id": 7,
      "device_id": 0,
      "start_ns": 4879195581,
      "end_ns": 4879196573,
      "duration_ns": 992,
      "grid_dim": [
        3,
        1,
        1
      ],
      "block_dim": [
        128,
        1,
        1
      ],
      "metrics": {
        "raw": {}
      },
      "attribution_method": "unattributed",
      "confidence": "unattributed",
      "nvtx_range": null
    },
    {
      "kernel_id": "k_00064",
      "kernel_name": "triton_poi_fused__native_batch_6...",
      "demangled_name": null,
      "stream_id": 7,
      "device_id": 0,
      "start_ns": 4879282652,
      "end_ns": 4879289916,
      "duration_ns": 7264,
      "grid_dim": [
        6272,
        1,
        1
      ],
      "block_dim": [
        256,
        1,
        1
      ],
      "metrics": {
        "raw": {}
      },
      "attribution_method": "unattributed",
      "confidence": "unattributed",
      "nvtx_range": null
    },
    {
      "kernel_id": "k_00065",
      "kernel_name": "triton_poi_fused__native_batch_7...",
      "demangled_name": null,
      "stream_id": 7,
      "device_id": 0,
      "start_ns": 4879304508,
      "end_ns": 4879305532,
      "duration_ns": 1024,
      "grid_dim": [
        1,
        32,
        1
      ],
      "block_dim": [
        128,
        1,
        1
      ],
      "metrics": {
        "raw": {}
      },
      "attribution_method": "unattributed",
      "confidence": "unattributed",
      "nvtx_range": null
    },
    {
      "kernel_id": "k_00067",
      "kernel_name": "triton_poi_fused__native_batch_8...",
      "demangled_name": null,
      "stream_id": 7,
      "device_id": 0,
      "start_ns": 4879355228,
      "end_ns": 4879366812,
      "duration_ns": 11584,
      "grid_dim": [
        12544,
        1,
        1
      ],
      "block_dim": [
        256,
        1,
        1
      ],
      "metrics": {
        "raw": {}
      },
      "attribution_method": "unattributed",
      "confidence": "unattributed",
      "nvtx_range": null
    },
    {
      "kernel_id": "k_00068",
      "kernel_name": "triton_poi_fused__native_batch_9...",
      "demangled_name": null,
      "stream_id": 7,
      "device_id": 0,
      "start_ns": 4879376892,
      "end_ns": 4879378364,
      "duration_ns": 1472,
      "grid_dim": [
        1,
        1,
        1
      ],
      "block_dim": [
        256,
        1,
        1
      ],
      "metrics": {
        "raw": {}
      },
      "attribution_method": "unattributed",
      "confidence": "unattributed",
      "nvtx_range": null
    },
    {
      "kernel_id": "k_00070",
      "kernel_name": "triton_poi_fused__native_batch_10...",
      "demangled_name": null,
      "stream_id": 7,
      "device_id": 0,
      "start_ns": 4879435675,
      "end_ns": 4879447515,
      "duration_ns": 11840,
      "grid_dim": [
        12544,
        1,
        1
      ],
      "block_dim": [
        256,
        1,
        1
      ],
      "metrics": {
        "raw": {}
      },
      "attribution_method": "unattributed",
      "confidence": "unattributed",
      "nvtx_range": null
    },
    {
      "kernel_id": "k_00071",
      "kernel_name": "triton_poi_fused__native_batch_11...",
      "demangled_name": null,
      "stream_id": 7,
      "device_id": 0,
      "start_ns": 4879457371,
      "end_ns": 4879459387,
      "duration_ns": 2016,
      "grid_dim": [
        8,
        1,
        1
      ],
      "block_dim": [
        256,
        1,
        1
      ],
      "metrics": {
        "raw": {}
      },
      "attribution_method": "unattributed",
      "confidence": "unattributed",
      "nvtx_range": null
    },
    {
      "kernel_id": "k_00073",
      "kernel_name": "triton_poi_fused__native_batch_12...",
      "demangled_name": null,
      "stream_id": 7,
      "device_id": 0,
      "start_ns": 4879529755,
      "end_ns": 4879551834,
      "duration_ns": 22079,
      "grid_dim": [
        25088,
        1,
        1
      ],
      "block_dim": [
        256,
        1,
        1
      ],
      "metrics": {
        "raw": {}
      },
      "attribution_method": "unattributed",
      "confidence": "unattributed",
      "nvtx_range": null
    },
    {
      "kernel_id": "k_00074",
      "kernel_name": "triton_poi_fused__native_batch_1...",
      "demangled_name": null,
      "stream_id": 7,
      "device_id": 0,
      "start_ns": 4879576410,
      "end_ns": 4879577370,
      "duration_ns": 960,
      "grid_dim": [
        2,
        1,
        1
      ],
      "block_dim": [
        128,
        1,
        1
      ],
      "metrics": {
        "raw": {}
      },
      "attribution_method": "unattributed",
      "confidence": "unattributed",
      "nvtx_range": null
    },
    {
      "kernel_id": "k_00076",
      "kernel_name": "triton_poi_fused__native_batch_2...",
      "demangled_name": null,
      "stream_id": 7,
      "device_id": 0,
      "start_ns": 4879634842,
      "end_ns": 4879639258,
      "duration_ns": 4416,
      "grid_dim": [
        1568,
        1,
        1
      ],
      "block_dim": [
        128,
        1,
        1
      ],
      "metrics": {
        "raw": {}
      },
      "attribution_method": "unattributed",
      "confidence": "unattributed",
      "nvtx_range": null
    },
    {
      "kernel_id": "k_00077",
      "kernel_name": "triton_poi_fused__native_batch_3...",
      "demangled_name": null,
      "stream_id": 7,
      "device_id": 0,
      "start_ns": 4879653818,
      "end_ns": 4879654842,
      "duration_ns": 1024,
      "grid_dim": [
        1,
        4,
        1
      ],
      "block_dim": [
        128,
        1,
        1
      ],
      "metrics": {
        "raw": {}
      },
      "attribution_method": "unattributed",
      "confidence": "unattributed",
      "nvtx_range": null
    },
    {
      "kernel_id": "k_00079",
      "kernel_name": "triton_poi_fused__native_batch_4...",
      "demangled_name": null,
      "stream_id": 7,
      "device_id": 0,
      "start_ns": 4879695193,
      "end_ns": 4879702425,
      "duration_ns": 7232,
      "grid_dim": [
        3136,
        1,
        1
      ],
      "block_dim": [
        128,
        1,
        1
      ],
      "metrics": {
        "raw": {}
      },
      "attribution_method": "unattributed",
      "confidence": "unattributed",
      "nvtx_range": null
    },
    {
      "kernel_id": "k_00080",
      "kernel_name": "triton_poi_fused__native_batch_5...",
      "demangled_name": null,
      "stream_id": 7,
      "device_id": 0,
      "start_ns": 4879715705,
      "end_ns": 4879716857,
      "duration_ns": 1152,
      "grid_dim": [
        3,
        1,
        1
      ],
      "block_dim": [
        128,
        1,
        1
      ],
      "metrics": {
        "raw": {}
      },
      "attribution_method": "unattributed",
      "confidence": "unattributed",
      "nvtx_range": null
    },
    {
      "kernel_id": "k_00082",
      "kernel_name": "triton_poi_fused__native_batch_6...",
      "demangled_name": null,
      "stream_id": 7,
      "device_id": 0,
      "start_ns": 4879766649,
      "end_ns": 4879773753,
      "duration_ns": 7104,
      "grid_dim": [
        6272,
        1,
        1
      ],
      "block_dim": [
        256,
        1,
        1
      ],
      "metrics": {
        "raw": {}
      },
      "attribution_method": "unattributed",
      "confidence": "unattributed",
      "nvtx_range": null
    },
    {
      "kernel_id": "k_00083",
      "kernel_name": "triton_poi_fused__native_batch_7...",
      "demangled_name": null,
      "stream_id": 7,
      "device_id": 0,
      "start_ns": 4879786201,
      "end_ns": 4879787193,
      "duration_ns": 992,
      "grid_dim": [
        1,
        32,
        1
      ],
      "block_dim": [
        128,
        1,
        1
      ],
      "metrics": {
        "raw": {}
      },
      "attribution_method": "unattributed",
      "confidence": "unattributed",
      "nvtx_range": null
    },
    {
      "kernel_id": "k_00085",
      "kernel_name": "triton_poi_fused__native_batch_8...",
      "demangled_name": null,
      "stream_id": 7,
      "device_id": 0,
      "start_ns": 4879828152,
      "end_ns": 4879839064,
      "duration_ns": 10912,
      "grid_dim": [
        12544,
        1,
        1
      ],
      "block_dim": [
        256,
        1,
        1
      ],
      "metrics": {
        "raw": {}
      },
      "attribution_method": "unattributed",
      "confidence": "unattributed",
      "nvtx_range": null
    },
    {
      "kernel_id": "k_00086",
      "kernel_name": "triton_poi_fused__native_batch_9...",
      "demangled_name": null,
      "stream_id": 7,
      "device_id": 0,
      "start_ns": 4879845496,
      "end_ns": 4879847032,
      "duration_ns": 1536,
      "grid_dim": [
        1,
        1,
        1
      ],
      "block_dim": [
        256,
        1,
        1
      ],
      "metrics": {
        "raw": {}
      },
      "attribution_method": "unattributed",
      "confidence": "unattributed",
      "nvtx_range": null
    },
    {
      "kernel_id": "k_00088",
      "kernel_name": "triton_poi_fused__native_batch_10...",
      "demangled_name": null,
      "stream_id": 7,
      "device_id": 0,
      "start_ns": 4879889144,
      "end_ns": 4879899736,
      "duration_ns": 10592,
      "grid_dim": [
        12544,
        1,
        1
      ],
      "block_dim": [
        256,
        1,
        1
      ],
      "metrics": {
        "raw": {}
      },
      "attribution_method": "unattributed",
      "confidence": "unattributed",
      "nvtx_range": null
    },
    {
      "kernel_id": "k_00089",
      "kernel_name": "triton_poi_fused__native_batch_11...",
      "demangled_name": null,
      "stream_id": 7,
      "device_id": 0,
      "start_ns": 4879903064,
      "end_ns": 4879905144,
      "duration_ns": 2080,
      "grid_dim": [
        8,
        1,
        1
      ],
      "block_dim": [
        256,
        1,
        1
      ],
      "metrics": {
        "raw": {}
      },
      "attribution_method": "unattributed",
      "confidence": "unattributed",
      "nvtx_range": null
    },
    {
      "kernel_id": "k_00091",
      "kernel_name": "triton_poi_fused__native_batch_12...",
      "demangled_name": null,
      "stream_id": 7,
      "device_id": 0,
      "start_ns": 4879968023,
      "end_ns": 4879989111,
      "duration_ns": 21088,
      "grid_dim": [
        25088,
        1,
        1
      ],
      "block_dim": [
        256,
        1,
        1
      ],
      "metrics": {
        "raw": {}
      },
      "attribution_method": "unattributed",
      "confidence": "unattributed",
      "nvtx_range": null
    }
  ],
  "warnings": [
    "k_00000 (distribution_elementwise_grid_stride_kernel): flagged as initialization kernel",
    "k_00001 (elementwise_kernel): flagged as initialization kernel",
    "k_00002 (triton_poi_fused__native_batch_1...): flagged as initialization kernel",
    "k_00003 (conv2d_c1_k1_nhwc): flagged as initialization kernel",
    "k_00004 (triton_poi_fused__native_batch_2...): flagged as initialization kernel",
    "k_00005 (triton_poi_fused__native_batch_3...): flagged as initialization kernel",
    "k_00006 (Kernel2): flagged as initialization kernel",
    "k_00007 (triton_poi_fused__native_batch_4...): flagged as initialization kernel",
    "k_00008 (triton_poi_fused__native_batch_5...): flagged as initialization kernel",
    "k_00009 (conv2d_c1_k1_nhwc): flagged as initialization kernel",
    "k_00010 (triton_poi_fused__native_batch_6...): flagged as initialization kernel",
    "k_00011 (triton_poi_fused__native_batch_7...): flagged as initialization kernel",
    "k_00012 (Kernel2): flagged as initialization kernel",
    "k_00013 (triton_poi_fused__native_batch_8...): flagged as initialization kernel",
    "k_00014 (triton_poi_fused__native_batch_9...): flagged as initialization kernel",
    "k_00015 (conv2d_c1_k1_nhwc): flagged as initialization kernel",
    "k_00016 (triton_poi_fused__native_batch_10...): flagged as initialization kernel",
    "k_00017 (triton_poi_fused__native_batch_11...): flagged as initialization kernel",
    "k_00018 (Kernel2): flagged as initialization kernel",
    "k_00019 (triton_poi_fused__native_batch_12...): flagged as initialization kernel",
    "k_00020 (triton_poi_fused__native_batch_1...): flagged as initialization kernel",
    "k_00021 (conv2d_c1_k1_nhwc): flagged as initialization kernel",
    "k_00022 (triton_poi_fused__native_batch_2...): flagged as initialization kernel",
    "k_00023 (triton_poi_fused__native_batch_3...): flagged as initialization kernel",
    "k_00024 (Kernel2): flagged as initialization kernel",
    "k_00025 (triton_poi_fused__native_batch_4...): flagged as initialization kernel",
    "k_00026 (triton_poi_fused__native_batch_5...): flagged as initialization kernel",
    "k_00027 (conv2d_c1_k1_nhwc): flagged as initialization kernel",
    "k_00028 (triton_poi_fused__native_batch_6...): flagged as initialization kernel",
    "k_00029 (triton_poi_fused__native_batch_7...): flagged as initialization kernel",
    "k_00030 (Kernel2): flagged as initialization kernel",
    "k_00031 (triton_poi_fused__native_batch_8...): flagged as initialization kernel",
    "k_00032 (triton_poi_fused__native_batch_9...): flagged as initialization kernel",
    "k_00033 (conv2d_c1_k1_nhwc): flagged as initialization kernel",
    "k_00034 (triton_poi_fused__native_batch_10...): flagged as initialization kernel",
    "k_00035 (triton_poi_fused__native_batch_11...): flagged as initialization kernel",
    "k_00036 (Kernel2): flagged as initialization kernel",
    "k_00037 (triton_poi_fused__native_batch_12...): flagged as initialization kernel",
    "k_00038 (triton_poi_fused__native_batch_1...): flagged as initialization kernel",
    "k_00039 (conv2d_c1_k1_nhwc): flagged as initialization kernel",
    "k_00040 (triton_poi_fused__native_batch_2...): flagged as initialization kernel",
    "k_00041 (triton_poi_fused__native_batch_3...): flagged as initialization kernel",
    "k_00042 (Kernel2): flagged as initialization kernel",
    "k_00043 (triton_poi_fused__native_batch_4...): flagged as initialization kernel",
    "k_00044 (triton_poi_fused__native_batch_5...): flagged as initialization kernel",
    "k_00045 (conv2d_c1_k1_nhwc): flagged as initialization kernel",
    "k_00046 (triton_poi_fused__native_batch_6...): flagged as initialization kernel",
    "k_00047 (triton_poi_fused__native_batch_7...): flagged as initialization kernel",
    "k_00048 (Kernel2): flagged as initialization kernel",
    "k_00049 (triton_poi_fused__native_batch_8...): flagged as initialization kernel",
    "k_00050 (triton_poi_fused__native_batch_9...): flagged as initialization kernel",
    "k_00051 (conv2d_c1_k1_nhwc): flagged as initialization kernel",
    "k_00052 (triton_poi_fused__native_batch_10...): flagged as initialization kernel",
    "k_00053 (triton_poi_fused__native_batch_11...): flagged as initialization kernel",
    "k_00054 (Kernel2): flagged as initialization kernel",
    "k_00055 (triton_poi_fused__native_batch_12...): flagged as initialization kernel"
  ]
}